term.py
py_term-0.7.data/scripts/term.py
py_term-0.7.dist-info/LICENSE
py_term-0.7.dist-info/METADATA
py_term-0.7.dist-info/WHEEL
py_term-0.7.dist-info/top_level.txt
py_term-0.7.dist-info/RECORD
